Metadata-Version: 2.1
Name: scons-tool-doxyfile
Version: 0.2.0
Summary: SCons tool to generate Doxyfile for Doxygen
Home-page: https://github.com/ptomulik/scons-tool-doxyfile
Author: Paweł Tomulik
Author-email: ptomulik@meil.pw.edu.pl
License: UNKNOWN
Platform: UNKNOWN
Requires-Python: >=2.7
